{"contract":"0xeA46E03C1c0aE3a1D3c93b98EF2d99915BD393A6","count":10,"tokens":[{"id":1,"owner":"0x26882bea46545505db4e58f8cf21680193f336e6","seed":2482190054,"mint_ts":1781621915,"species":1,"github":"yonecode","dna":"{\"species\":1,\"lang\":\"JavaScript\",\"archetype\":\"Thoughtful Builder\"}"},{"id":2,"owner":"0x000000000000000000000000000000000000dEaD","seed":57005,"mint_ts":1781622340,"species":2,"github":"torvalds","dna":"{\"species\":2,\"lang\":\"C\",\"archetype\":\"System Architect\"}"},{"id":3,"owner":"0xcf29a1d22392f93a876af2690be09de62f2620b8","seed":791027896,"mint_ts":1781643090,"species":4,"github":"cepuyut","dna":"{\"species\":4,\"lang\":\"unknown\",\"archetype\":\"web3 contributor\"}"},{"id":4,"owner":"0xd79f3c5187cab6eaa76b0c028e07c1a93936e683","seed":959899267,"mint_ts":1781658971,"species":1,"github":"rivaleuc","dna":"{\"species\":1,\"lang\":\"JavaScript\",\"archetype\":\"Creative Catalyst\"}"},{"id":5,"owner":"0xaf7169e1c3c759e668cf106b69ddce085d464aea","seed":1564887786,"mint_ts":1781659929,"species":4,"github":"JoaquinBN","dna":"{\"species\":4,\"lang\":\"unknown\",\"archetype\":\"Polyglot Pioneer\"}"},{"id":6,"owner":"0x3b49b8ed8b0f59eea6805f87673920f2fd43da97","seed":4249082519,"mint_ts":1781660716,"species":4,"github":"","dna":""},{"id":7,"owner":"0xdad0d6a5cb24db007694a713701d286a2bbbece3","seed":733736163,"mint_ts":1781667898,"species":4,"github":"globabe","dna":"{\"species\":4,\"lang\":\"unknown\",\"archetype\":\"Polyglot\"}"},{"id":8,"owner":"0x01863b065d8d8ed5397b266df2d121384e0b7d40","seed":1309375808,"mint_ts":1781706884,"species":4,"github":"Carbofozzz","dna":"{\"species\":4,\"lang\":\"unknown\",\"archetype\":\"Polyglot\"}"},{"id":9,"owner":"0x8934189422cdad434d72adb1691d5609f56223e4","seed":4116849636,"mint_ts":1781706894,"species":4,"github":"Jr-kenny","dna":"{\"species\":4,\"lang\":\"unknown\",\"archetype\":\"Polyglot Pioneer\"}"},{"id":10,"owner":"0x5905c9dea6ae52aa0947d8f7f218263889edfc4e","seed":2314075214,"mint_ts":1781706925,"species":1,"github":"TS-mfon","dna":"{\"species\":1,\"lang\":\"TypeScript\",\"archetype\":\"Frontend Artisan\"}"}]}